beanie/__init__.py
beanie/exceptions.py
beanie/operators.py
beanie/py.typed
beanie/executors/__init__.py
beanie/executors/migrate.py
beanie/migrations/__init__.py
beanie/migrations/database.py
beanie/migrations/models.py
beanie/migrations/runner.py
beanie/migrations/template.py
beanie/migrations/utils.py
beanie/migrations/controllers/__init__.py
beanie/migrations/controllers/base.py
beanie/migrations/controllers/free_fall.py
beanie/migrations/controllers/iterative.py
beanie/odm/__init__.py
beanie/odm/actions.py
beanie/odm/bulk.py
beanie/odm/cache.py
beanie/odm/documents.py
beanie/odm/enums.py
beanie/odm/fields.py
beanie/odm/models.py
beanie/odm/registry.py
beanie/odm/union_doc.py
beanie/odm/views.py
beanie/odm/custom_types/__init__.py
beanie/odm/custom_types/decimal.py
beanie/odm/custom_types/re.py
beanie/odm/custom_types/bson/__init__.py
beanie/odm/custom_types/bson/binary.py
beanie/odm/interfaces/__init__.py
beanie/odm/interfaces/aggregate.py
beanie/odm/interfaces/aggregation_methods.py
beanie/odm/interfaces/clone.py
beanie/odm/interfaces/detector.py
beanie/odm/interfaces/find.py
beanie/odm/interfaces/getters.py
beanie/odm/interfaces/inheritance.py
beanie/odm/interfaces/session.py
beanie/odm/interfaces/setters.py
beanie/odm/interfaces/update.py
beanie/odm/operators/__init__.py
beanie/odm/operators/find/__init__.py
beanie/odm/operators/find/array.py
beanie/odm/operators/find/bitwise.py
beanie/odm/operators/find/comparison.py
beanie/odm/operators/find/element.py
beanie/odm/operators/find/evaluation.py
beanie/odm/operators/find/geospatial.py
beanie/odm/operators/find/logical.py
beanie/odm/operators/update/__init__.py
beanie/odm/operators/update/array.py
beanie/odm/operators/update/bitwise.py
beanie/odm/operators/update/general.py
beanie/odm/queries/__init__.py
beanie/odm/queries/aggregation.py
beanie/odm/queries/cursor.py
beanie/odm/queries/delete.py
beanie/odm/queries/find.py
beanie/odm/queries/update.py
beanie/odm/settings/__init__.py
beanie/odm/settings/base.py
beanie_mongoengine_compat-1.30.1.dist-info/entry_points.txt
beanie_mongoengine_compat-1.30.1.dist-info/licenses/LICENSE
beanie_mongoengine_compat-1.30.1.dist-info/WHEEL
beanie_mongoengine_compat-1.30.1.dist-info/METADATA
beanie_mongoengine_compat-1.30.1.dist-info/RECORD
