Metadata-Version: 2.4
Name: beanie-mongoengine-compat
Version: 1.30.1
Summary: Asynchronous Python ODM for MongoDB with mongoengine-compatible Links (ObjectId instead of DBRef)
Keywords: mongodb,odm,orm,pydantic,mongo,async,python,mongoengine,compatibility
Author-email: Roman Right <roman-right@protonmail.com>
Requires-Python: >=3.9,<4.0
Classifier: License :: OSI Approved :: Apache Software License
Classifier: Development Status :: 5 - Production/Stable
Classifier: Intended Audience :: Developers
Classifier: Operating System :: OS Independent
Classifier: Topic :: Database
Classifier: Topic :: Software Development :: Libraries :: Python Modules
Classifier: Typing :: Typed
License-File: LICENSE
Requires-Dist: pydantic>=1.10.18,<3.0
Requires-Dist: motor>=2.5.0,<4.0.0
Requires-Dist: click>=7
Requires-Dist: toml
Requires-Dist: lazy-model==0.2.0
Requires-Dist: typing-extensions>=4.7
Requires-Dist: motor[aws]>=2.5.0,<4.0.0 ; extra == "aws"
Requires-Dist: motor[encryption]>=2.5.0,<4.0.0 ; extra == "encryption"
Requires-Dist: motor[gssapi]>=2.5.0,<4.0.0 ; extra == "gssapi"
Requires-Dist: motor[ocsp]>=2.5.0,<4.0.0 ; extra == "ocsp"
Requires-Dist: beanie-batteries-queue>=0.2 ; extra == "queue"
Requires-Dist: motor[snappy]>=2.5.0,<4.0.0 ; extra == "snappy"
Requires-Dist: motor[zstd]>=2.5.0,<4.0.0 ; extra == "zstd"
Project-URL: homepage, https://github.com/wayneg123/beanie-mongoengine-compat
Project-URL: original, https://github.com/roman-right/beanie
Project-URL: repository, https://github.com/wayneg123/beanie-mongoengine-compat
Provides-Extra: aws
Provides-Extra: encryption
Provides-Extra: gssapi
Provides-Extra: ocsp
Provides-Extra: queue
Provides-Extra: snappy
Provides-Extra: zstd
